{
  "buckets": {
    "clean": 105314,
    "not_real_macho": 7586,
    "other_sig_invalid": 1,
    "page_hash_mismatch": 50,
    "unsigned": 105921
  },
  "buckets_by_arch": {
    "arm": {
      "not_real_macho": 2,
      "unsigned": 6
    },
    "arm64": {
      "clean": 97006,
      "not_real_macho": 20,
      "page_hash_mismatch": 29,
      "unsigned": 7788
    },
    "arm64e": {
      "clean": 13,
      "not_real_macho": 40
    },
    "cpu_0x00000001/0x00000000": {
      "clean": 2
    },
    "cpu_0x00000002/0x00000000": {
      "not_real_macho": 2
    },
    "cpu_0x00000004/0x00000000": {
      "unsigned": 2
    },
    "cpu_0x00000005/0x00000000": {
      "not_real_macho": 2
    },
    "cpu_0x00000012/0x00000000": {
      "not_real_macho": 87
    },
    "cpu_0x00000012/0x0000000a": {
      "not_real_macho": 10
    },
    "cpu_0x00000012/0x00000064": {
      "not_real_macho": 2
    },
    "cpu_0x01000012/0x00000000": {
      "not_real_macho": 15
    },
    "i386": {
      "clean": 113,
      "not_real_macho": 2,
      "unsigned": 55
    },
    "unknown": {
      "not_real_macho": 7352
    },
    "x86_64": {
      "clean": 8180,
      "not_real_macho": 52,
      "other_sig_invalid": 1,
      "page_hash_mismatch": 21,
      "unsigned": 98070
    }
  },
  "channel_label": "nixpkgs-25.11-darwin @ 25b257cc0377 (2026-05-08)",
  "coverage": {
    "not_real_macho": 7586,
    "page_size_zero_cds": 0,
    "scanner_errors": 0,
    "sha1_only_cds": 0
  },
  "generated_at": "2026-05-08 08:32:45 UTC",
  "other_sig_invalid": {
    "packages": 1,
    "slices": 1
  },
  "page_hash_mismatch": {
    "by_signature_class": {
      "C2": 43,
      "L": 7
    },
    "by_signer": {
      "codesign_signed": 43,
      "linker_signed": 7
    },
    "packages": 13,
    "packages_list": [
      "avalonia-ilspy-7.2-rc",
      "cmdargs-browser-0.1.4",
      "esy-0.8.0",
      "httptoolkit-1.24.4",
      "libtorch-2.9.0",
      "shogihome-1.27.1",
      "swift-5.10.1",
      "swift-5.10.1-lib",
      "tailwindcss_4-4.1.18",
      "teams-for-linux-2.8.0"
    ],
    "slices": 50
  },
  "paths_by_status": {
    "ok": 171573
  },
  "paths_scanned": 171573,
  "slices_by_arch": {
    "arm": 8,
    "arm64": 104843,
    "arm64e": 53,
    "cpu_0x00000001/0x00000000": 2,
    "cpu_0x00000002/0x00000000": 2,
    "cpu_0x00000004/0x00000000": 2,
    "cpu_0x00000005/0x00000000": 2,
    "cpu_0x00000012/0x00000000": 87,
    "cpu_0x00000012/0x0000000a": 10,
    "cpu_0x00000012/0x00000064": 2,
    "cpu_0x01000012/0x00000000": 15,
    "i386": 170,
    "unknown": 7352,
    "x86_64": 106324
  },
  "slices_total": 218872
}
